{"63_0001":{"id":"63_0001","name":"Zift\u00e1, Mu\u1e29\u0101faz\u0327at al Gharb\u012byah"},"63_0002":{"id":"63_0002","name":"Toukh, Mu\u1e29\u0101faz\u0327at al Qaly\u016bb\u012byah"},"63_0003":{"id":"63_0003","name":"Tanda, Mu\u1e29\u0101faz\u0327at al Gharb\u012byah"},"63_0004":{"id":"63_0004","name":"\u0162\u0101miyah, Mu\u1e29\u0101faz\u0327at al Fayy\u016bm"},"63_0005":{"id":"63_0005","name":"\u0162alkh\u0101, Mu\u1e29\u0101faz\u0327at ad Daqahl\u012byah"},"63_0006":{"id":"63_0006","name":"Tal\u0101, Mu\u1e29\u0101faz\u0327at al Min\u016bf\u012byah"},"63_0007":{"id":"63_0007","name":"\u0162ah\u0163\u0101, S\u016bh\u0101j"},"63_0008":{"id":"63_0008","name":"Sumus\u0163\u0101 as Sul\u0163\u0101n\u012b, Mu\u1e29\u0101faz\u0327at Ban\u012b Suwayf"},"63_0009":{"id":"63_0009","name":"Sohag, S\u016bh\u0101j"},"63_0010":{"id":"63_0010","name":"S\u012bd\u012b S\u0101lim, Kafr ash Shaykh"},"63_0011":{"id":"63_0011","name":"Shirb\u012bn, Mu\u1e29\u0101faz\u0327at ad Daqahl\u012byah"},"63_0012":{"id":"63_0012","name":"Shib\u012bn al Qan\u0101\u0163ir, Mu\u1e29\u0101faz\u0327at al Qaly\u016bb\u012byah"},"63_0013":{"id":"63_0013","name":"Shib\u012bn al Kawm, Mu\u1e29\u0101faz\u0327at al Min\u016bf\u012byah"},"63_0014":{"id":"63_0014","name":"Samann\u016bd, Mu\u1e29\u0101faz\u0327at al Gharb\u012byah"},"63_0015":{"id":"63_0015","name":"Sam\u0101l\u016b\u0163, Al Miny\u0101"},"63_0016":{"id":"63_0016","name":"Rosetta, Al Bu\u1e29ayrah"},"63_0017":{"id":"63_0017","name":"Ras Gharib, Red Sea"},"63_0018":{"id":"63_0018","name":"Quwaysin\u0101, Mu\u1e29\u0101faz\u0327at al Min\u016bf\u012byah"},"63_0019":{"id":"63_0019","name":"Qu\u0163\u016br, Mu\u1e29\u0101faz\u0327at al Gharb\u012byah"},"63_0020":{"id":"63_0020","name":"Kousa, Qin\u0101"},"63_0021":{"id":"63_0021","name":"Qin\u0101"},"63_0022":{"id":"63_0022","name":"Qaly\u016bb, Mu\u1e29\u0101faz\u0327at al Qaly\u016bb\u012byah"},"63_0023":{"id":"63_0023","name":"Naj\u2018 \u1e28amm\u0101d\u012b, Qin\u0101"},"63_0024":{"id":"63_0024","name":"Minyat an Na\u015fr, Mu\u1e29\u0101faz\u0327at ad Daqahl\u012byah"},"63_0025":{"id":"63_0025","name":"Min\u016bf, Mu\u1e29\u0101faz\u0327at al Min\u016bf\u012byah"},"63_0026":{"id":"63_0026","name":"Ma\u0163\u0101y, Al Miny\u0101"},"63_0027":{"id":"63_0027","name":"Masht\u016bl as S\u016bq, Eastern Province"},"63_0028":{"id":"63_0028","name":"Mersa Matruh, Mu\u1e29\u0101faz\u0327at Ma\u0163r\u016b\u1e29"},"63_0029":{"id":"63_0029","name":"Manfal\u016b\u0163, Asy\u016b\u0163"},"63_0030":{"id":"63_0030","name":"Mallaw\u012b, Al Miny\u0101"},"63_0031":{"id":"63_0031","name":"Mad\u012bnat Sittah Ukt\u016bbar, Al J\u012bzah"},"63_0032":{"id":"63_0032","name":"Kawm Umb\u016b, Asw\u0101n"},"63_0033":{"id":"63_0033","name":"Kawm \u1e28am\u0101dah, Al Bu\u1e29ayrah"},"63_0034":{"id":"63_0034","name":"Kafr \u015eaqr, Eastern Province"},"63_0035":{"id":"63_0035","name":"Kafr az Zayy\u0101t, Mu\u1e29\u0101faz\u0327at al Gharb\u012byah"},"63_0036":{"id":"63_0036","name":"Kafr ash Shaykh"},"63_0037":{"id":"63_0037","name":"Kafr ad Daww\u0101r, Al Bu\u1e29ayrah"},"63_0038":{"id":"63_0038","name":"Juhaynah, S\u016bh\u0101j"},"63_0039":{"id":"63_0039","name":"Jirj\u0101, S\u016bh\u0101j"},"63_0040":{"id":"63_0040","name":"\u2018Izbat al Burj, Mu\u1e29\u0101faz\u0327at ad Daqahl\u012byah"},"63_0041":{"id":"63_0041","name":"I\u0163s\u0101, Mu\u1e29\u0101faz\u0327at al Fayy\u016bm"},"63_0042":{"id":"63_0042","name":"Isn\u0101, Qin\u0101"},"63_0043":{"id":"63_0043","name":"Idk\u016b, Al Bu\u1e29ayrah"},"63_0044":{"id":"63_0044","name":"Idf\u016b, Asw\u0101n"},"63_0045":{"id":"63_0045","name":"Ibshaw\u0101y, Mu\u1e29\u0101faz\u0327at al Fayy\u016bm"},"63_0046":{"id":"63_0046","name":"\u1e28alw\u0101n, Cairo Governorate"},"63_0047":{"id":"63_0047","name":"Hihy\u0101, Eastern Province"},"63_0048":{"id":"63_0048","name":"\u1e28awsh \u2018\u012as\u00e1, Al Bu\u1e29ayrah"},"63_0049":{"id":"63_0049","name":"Fuwwah, Kafr ash Shaykh"},"63_0050":{"id":"63_0050","name":"Farsh\u016b\u0163, Qin\u0101"},"63_0051":{"id":"63_0051","name":"F\u0101rask\u016br, Dumy\u0101\u0163"},"63_0052":{"id":"63_0052","name":"F\u0101q\u016bs, Eastern Province"},"63_0053":{"id":"63_0053","name":"Damietta, Dumy\u0101\u0163"},"63_0054":{"id":"63_0054","name":"Diyarb Najm, Eastern Province"},"63_0055":{"id":"63_0055","name":"Dis\u016bq, Kafr ash Shaykh"},"63_0056":{"id":"63_0056","name":"Dishn\u0101, Qin\u0101"},"63_0057":{"id":"63_0057","name":"Dikirnis, Mu\u1e29\u0101faz\u0327at ad Daqahl\u012byah"},"63_0058":{"id":"63_0058","name":"Dayr\u016b\u0163, Asy\u016b\u0163"},"63_0059":{"id":"63_0059","name":"Dayr Maw\u0101s, Al Miny\u0101"},"63_0060":{"id":"63_0060","name":"Damanh\u016br, Al Bu\u1e29ayrah"},"63_0061":{"id":"63_0061","name":"B\u016bsh, Mu\u1e29\u0101faz\u0327at Ban\u012b Suwayf"},"63_0062":{"id":"63_0062","name":"Port Said, Mu\u1e29\u0101faz\u0327at B\u016br Sa\u2018\u012bd"},"63_0063":{"id":"63_0063","name":"B\u016br Saf\u0101jah, Red Sea"},"63_0064":{"id":"63_0064","name":"Bilq\u0101s, Mu\u1e29\u0101faz\u0327at ad Daqahl\u012byah"},"63_0065":{"id":"63_0065","name":"Bilbays, Eastern Province"},"63_0066":{"id":"63_0066","name":"Basy\u016bn, Mu\u1e29\u0101faz\u0327at al Gharb\u012byah"},"63_0067":{"id":"63_0067","name":"Ban\u012b Suwayf, Mu\u1e29\u0101faz\u0327at Ban\u012b Suwayf"},"63_0068":{"id":"63_0068","name":"Ban\u012b Maz\u0101r, Al Miny\u0101"},"63_0069":{"id":"63_0069","name":"Banh\u0101, Mu\u1e29\u0101faz\u0327at al Qaly\u016bb\u012byah"},"63_0070":{"id":"63_0070","name":"Zagazig, Eastern Province"},"63_0071":{"id":"63_0071","name":"Aws\u012bm, Al J\u012bzah"},"63_0072":{"id":"63_0072","name":"At Tall al Kab\u012br, Al Ism\u0101\u2018\u012bl\u012byah"},"63_0073":{"id":"63_0073","name":"Asy\u016b\u0163"},"63_0074":{"id":"63_0074","name":"Aswan, Asw\u0101n"},"63_0075":{"id":"63_0075","name":"Suez, As Suways"},"63_0076":{"id":"63_0076","name":"A\u015f \u015eaff, Al J\u012bzah"},"63_0077":{"id":"63_0077","name":"Ash Shuhad\u0101\u2019, Mu\u1e29\u0101faz\u0327at al Min\u016bf\u012byah"},"63_0078":{"id":"63_0078","name":"Ashm\u016bn, Mu\u1e29\u0101faz\u0327at al Min\u016bf\u012byah"},"63_0079":{"id":"63_0079","name":"Al W\u0101si\u0163ah, Mu\u1e29\u0101faz\u0327at al Fayy\u016bm"},"63_0080":{"id":"63_0080","name":"Luxor"},"63_0081":{"id":"63_0081","name":"Al Q\u016b\u015f\u012byah, Asy\u016b\u0163"},"63_0082":{"id":"63_0082","name":"Al Qu\u015fayr, Red Sea"},"63_0083":{"id":"63_0083","name":"Al Qurayn, Eastern Province"},"63_0084":{"id":"63_0084","name":"Al Qan\u0101y\u0101t, Eastern Province"},"63_0085":{"id":"63_0085","name":"Al Qan\u0101\u0163ir al Khayr\u012byah, Mu\u1e29\u0101faz\u0327at al Qaly\u016bb\u012byah"},"63_0086":{"id":"63_0086","name":"Cairo, Cairo Governorate"},"63_0087":{"id":"63_0087","name":"Al Miny\u0101"},"63_0088":{"id":"63_0088","name":"Al Ma\u0163ar\u012byah, Mu\u1e29\u0101faz\u0327at ad Daqahl\u012byah"},"63_0089":{"id":"63_0089","name":"Al Manzilah, Mu\u1e29\u0101faz\u0327at ad Daqahl\u012byah"},"63_0090":{"id":"63_0090","name":"Al Man\u015f\u016brah, Mu\u1e29\u0101faz\u0327at ad Daqahl\u012byah"},"63_0091":{"id":"63_0091","name":"Al Mansh\u0101h, S\u016bh\u0101j"},"63_0092":{"id":"63_0092","name":"Al Ma\u1e29allah al Kubr\u00e1, Mu\u1e29\u0101faz\u0327at al Gharb\u012byah"},"63_0093":{"id":"63_0093","name":"Al Kh\u0101rijah, Mu\u1e29\u0101faz\u0327at al W\u0101d\u012b al Jad\u012bd"},"63_0094":{"id":"63_0094","name":"Al Kh\u0101nkah, Mu\u1e29\u0101faz\u0327at al Qaly\u016bb\u012byah"},"63_0095":{"id":"63_0095","name":"Al J\u012bzah"},"63_0096":{"id":"63_0096","name":"Al Jam\u0101l\u012byah, Mu\u1e29\u0101faz\u0327at ad Daqahl\u012byah"},"63_0097":{"id":"63_0097","name":"Ismailia, Al Ism\u0101\u2018\u012bl\u012byah"},"63_0098":{"id":"63_0098","name":"Alexandria"},"63_0099":{"id":"63_0099","name":"Al Ibr\u0101h\u012bm\u012byah, Eastern Province"},"63_0100":{"id":"63_0100","name":"Al \u1e28aw\u0101mid\u012byah, Al J\u012bzah"},"63_0101":{"id":"63_0101","name":"Al \u1e28\u0101m\u016bl, Kafr ash Shaykh"},"63_0102":{"id":"63_0102","name":"Hurghada, Red Sea"},"63_0103":{"id":"63_0103","name":"Al Fayy\u016bm, Mu\u1e29\u0101faz\u0327at al Fayy\u016bm"},"63_0104":{"id":"63_0104","name":"Al Fashn, Mu\u1e29\u0101faz\u0327at Ban\u012b Suwayf"},"63_0105":{"id":"63_0105","name":"Al Baw\u012b\u0163\u012b, Al J\u012bzah"},"63_0106":{"id":"63_0106","name":"Al Balyan\u0101, S\u016bh\u0101j"},"63_0107":{"id":"63_0107","name":"Al B\u0101j\u016br, Mu\u1e29\u0101faz\u0327at al Min\u016bf\u012byah"},"63_0108":{"id":"63_0108","name":"Al Bad\u0101r\u012b, Asy\u016b\u0163"},"63_0109":{"id":"63_0109","name":"Al \u2018Ayy\u0101\u0163, Al J\u012bzah"},"63_0110":{"id":"63_0110","name":"Arish, Sham\u0101l S\u012bn\u0101\u02bc"},"63_0111":{"id":"63_0111","name":"Akhm\u012bm, S\u016bh\u0101j"},"63_0112":{"id":"63_0112","name":"Aj\u0101, Mu\u1e29\u0101faz\u0327at ad Daqahl\u012byah"},"63_0113":{"id":"63_0113","name":"Ad Dilinj\u0101t, Al Bu\u1e29ayrah"},"63_0114":{"id":"63_0114","name":"Ab\u016b T\u012bj, Asy\u016b\u0163"},"63_0115":{"id":"63_0115","name":"Ab\u016b Qurq\u0101\u015f, Al Miny\u0101"},"63_0116":{"id":"63_0116","name":"Ab\u016b Kab\u012br, Eastern Province"},"63_0117":{"id":"63_0117","name":"Ab\u016b al Ma\u0163\u0101m\u012br, Al Bu\u1e29ayrah"},"63_0118":{"id":"63_0118","name":"Abn\u016bb, Asy\u016b\u0163"},"63_0119":{"id":"63_0119","name":"Az Zarq\u0101, Dumy\u0101\u0163"},"63_0120":{"id":"63_0120","name":"Ain Sukhna, As Suways"}}